ggce/__init__.py
ggce/logger.py
ggce/model.py
ggce/_tests/__init__.py
ggce/_tests/conftest.py
ggce/_tests/test_chkpt.py
ggce/_tests/test_engine_system.py
ggce/_tests/test_engine_terms.py
ggce/_tests/test_hp_fint.py
ggce/_tests/test_literature.py
ggce/_tests/test_literature_finT.py
ggce/_tests/test_model.py
ggce/_tests/test_utils_physics.py
ggce/_tests/mpi/setup_pytest_mpi.cfg
ggce/_tests/mpi/test_literature_mpi.py
ggce/_tests/petsc/setup_pytest_petsc_mpi.cfg
ggce/_tests/petsc/test_hp_fint_petsc.py
ggce/_tests/petsc/test_literature_finT_petsc.py
ggce/_tests/petsc/test_literature_petsc.py
ggce/_tests/petsc/test_literature_petsc_brigades.py
ggce/_tests/petsc/test_petsc_sysgen.py
ggce/engine/__init__.py
ggce/engine/equations.py
ggce/engine/system.py
ggce/engine/terms.py
ggce/executors/__init__.py
ggce/executors/solvers.py
ggce/executors/petsc4py/__init__.py
ggce/executors/petsc4py/base.py
ggce/executors/petsc4py/solvers.py
ggce/utils/__init__.py
ggce/utils/combinatorics.py
ggce/utils/physics.py
ggce/utils/utils.py
ggce-0.1.3.dist-info/LICENSE
ggce-0.1.3.dist-info/WHEEL
ggce-0.1.3.dist-info/METADATA
ggce-0.1.3.dist-info/RECORD
