Metadata-Version: 2.1
Name: ggce
Version: 0.1.3
Summary: Numerically exact Generalized Green's Function Cluster Expansion
Author-email: "Matthew R. Carbone" <mcarbone@bnl.gov>, Stepan Fomichev <fomichev@physics.ubc.ca>
Maintainer-email: "Matthew R. Carbone" <mcarbone@bnl.gov>, Stepan Fomichev <fomichev@physics.ubc.ca>
Requires-Python: >=3.7
Classifier: Development Status :: 2 - Pre-Alpha
Classifier: Natural Language :: English
Classifier: Programming Language :: Python :: 3 :: Only
Classifier: Programming Language :: Python :: 3.7
Classifier: Programming Language :: Python :: 3.8
Classifier: Programming Language :: Python :: 3.9
Classifier: Programming Language :: Python :: 3
Classifier: Topic :: Scientific/Engineering
Classifier: Intended Audience :: Developers
Classifier: Intended Audience :: Education
Classifier: Intended Audience :: Science/Research
Requires-Dist: numpy<1.24
Requires-Dist: scipy
Requires-Dist: loguru
Requires-Dist: monty
Requires-Dist: tqdm
Requires-Dist: sphinx ; extra == "doc"
Requires-Dist: numpydoc ; extra == "doc"
Requires-Dist: sphinx-copybutton ; extra == "doc"
Requires-Dist: sphinx_rtd_theme ; extra == "doc"
Requires-Dist: ipython ; extra == "doc"
Requires-Dist: matplotlib ; extra == "doc"
Requires-Dist: codecov ; extra == "test"
Requires-Dist: coverage ; extra == "test"
Requires-Dist: flake8 ; extra == "test"
Requires-Dist: pytest ; extra == "test"
Requires-Dist: pytest-cov ; extra == "test"
Requires-Dist: black ; extra == "test"
Requires-Dist: nbstripout ; extra == "test"
Requires-Dist: pre-commit ; extra == "test"
Provides-Extra: doc
Provides-Extra: test
